{"royapuram":{"total":137772,"source":"IndiaVotes / ECI, Tamil Nadu Assembly Election 2006","total_votes":95090,"poll_pct":69.0,"margin":13503},"harbour":{"total":105115,"source":"IndiaVotes / ECI, Tamil Nadu Assembly Election 2006","total_votes":60007,"poll_pct":57.1,"margin":410},"dr_radhakrishnan_nagar":{"total":239326,"source":"IndiaVotes / ECI, Tamil Nadu Assembly Election 2006","total_votes":167730,"poll_pct":70.1,"margin":18063},"park_town":{"total":117016,"source":"IndiaVotes / ECI, Tamil Nadu Assembly Election 2006","total_votes":72915,"poll_pct":62.3,"margin":6357},"perambur":{"total":268704,"source":"IndiaVotes / ECI, Tamil Nadu Assembly Election 2006","total_votes":182631,"poll_pct":68.0,"margin":2788},"purasawalkam":{"total":294352,"source":"IndiaVotes / ECI, Tamil Nadu Assembly Election 2006","total_votes":191680,"poll_pct":65.1,"margin":7385},"egmore":{"total":122297,"source":"IndiaVotes / ECI, Tamil Nadu Assembly Election 2006","total_votes":79326,"poll_pct":64.9,"margin":6480},"anna_nagar":{"total":352829,"source":"IndiaVotes / ECI, Tamil Nadu Assembly Election 2006","total_votes":217235,"poll_pct":61.6,"margin":12390},"theagaraya_nagar":{"total":242771,"source":"IndiaVotes / ECI, Tamil Nadu Assembly Election 2006","total_votes":152680,"poll_pct":62.9,"margin":16477},"thousand_lights":{"total":169506,"source":"IndiaVotes / ECI, Tamil Nadu Assembly Election 2006","total_votes":108295,"poll_pct":63.9,"margin":2468},"chepauk":{"total":105252,"source":"IndiaVotes / ECI, Tamil Nadu Assembly Election 2006","total_votes":67082,"poll_pct":63.7,"margin":8526},"triplicane":{"total":132523,"source":"IndiaVotes / ECI, Tamil Nadu Assembly Election 2006","total_votes":85505,"poll_pct":64.5,"margin":2776},"mylapore":{"total":235246,"source":"IndiaVotes / ECI, Tamil Nadu Assembly Election 2006","total_votes":147345,"poll_pct":62.6,"margin":1667},"saidapet":{"total":248483,"source":"IndiaVotes / ECI, Tamil Nadu Assembly Election 2006","total_votes":164396,"poll_pct":66.2,"margin":5905},"gummidipundi":{"total":195425,"source":"IndiaVotes / ECI, Tamil Nadu Assembly Election 2006","total_votes":156263,"poll_pct":80.0,"margin":229},"ponneri":{"total":248155,"source":"IndiaVotes / ECI, Tamil Nadu Assembly Election 2006","total_votes":175234,"poll_pct":70.6,"margin":11089},"thiruvottiyur":{"total":496267,"source":"IndiaVotes / ECI, Tamil Nadu Assembly Election 2006","total_votes":341404,"poll_pct":68.8,"margin":3447},"villivakkam":{"total":941112,"source":"IndiaVotes / ECI, Tamil Nadu Assembly Election 2006","total_votes":611251,"poll_pct":64.9,"margin":30116},"alandur":{"total":431953,"source":"IndiaVotes / ECI, Tamil Nadu Assembly Election 2006","total_votes":284421,"poll_pct":65.8,"margin":17910},"tambaram":{"total":872877,"source":"IndiaVotes / ECI, Tamil Nadu Assembly Election 2006","total_votes":561918,"poll_pct":64.4,"margin":48752},"tirupporur":{"total":247954,"source":"IndiaVotes / ECI, Tamil Nadu Assembly Election 2006","total_votes":162708,"poll_pct":65.6,"margin":10164},"chengalpattu":{"total":178466,"source":"IndiaVotes / ECI, Tamil Nadu Assembly Election 2006","total_votes":127479,"poll_pct":71.4,"margin":10213},"maduranthakam":{"total":154532,"source":"IndiaVotes / ECI, Tamil Nadu Assembly Election 2006","total_votes":117418,"poll_pct":76.0,"margin":3691},"acharapakkam":{"total":146977,"source":"IndiaVotes / ECI, Tamil Nadu Assembly Election 2006","total_votes":109003,"poll_pct":74.2,"margin":15856},"uthiramerur":{"total":182455,"source":"IndiaVotes / ECI, Tamil Nadu Assembly Election 2006","total_votes":144600,"poll_pct":79.3,"margin":12016},"kancheepuram":{"total":239201,"source":"IndiaVotes / ECI, Tamil Nadu Assembly Election 2006","total_votes":172828,"poll_pct":72.3,"margin":11284},"sriperumbudur":{"total":238710,"source":"IndiaVotes / ECI, Tamil Nadu Assembly Election 2006","total_votes":160042,"poll_pct":67.0,"margin":17794},"poonamallee":{"total":336248,"source":"IndiaVotes / ECI, Tamil Nadu Assembly Election 2006","total_votes":204112,"poll_pct":60.7,"margin":15330},"tiruvallur":{"total":188609,"source":"IndiaVotes / ECI, Tamil Nadu Assembly Election 2006","total_votes":133734,"poll_pct":70.9,"margin":8924},"tiruttani":{"total":164790,"source":"IndiaVotes / ECI, Tamil Nadu Assembly Election 2006","total_votes":122823,"poll_pct":74.5,"margin":916},"pallipet":{"total":173462,"source":"IndiaVotes / ECI, Tamil Nadu Assembly Election 2006","total_votes":126680,"poll_pct":73.0,"margin":7315},"arkonam":{"total":190314,"source":"IndiaVotes / ECI, Tamil Nadu Assembly Election 2006","total_votes":140786,"poll_pct":74.0,"margin":7556},"sholinghur":{"total":180495,"source":"IndiaVotes / ECI, Tamil Nadu Assembly Election 2006","total_votes":138114,"poll_pct":76.5,"margin":7916},"ranipet":{"total":227170,"source":"IndiaVotes / ECI, Tamil Nadu Assembly Election 2006","total_votes":168364,"poll_pct":74.1,"margin":32095},"arcot":{"total":160759,"source":"IndiaVotes / ECI, Tamil Nadu Assembly Election 2006","total_votes":123711,"poll_pct":77.0,"margin":11317},"katpadi":{"total":214702,"source":"IndiaVotes / ECI, Tamil Nadu Assembly Election 2006","total_votes":151135,"poll_pct":70.4,"margin":35147},"gudiyatham":{"total":178024,"source":"IndiaVotes / ECI, Tamil Nadu Assembly Election 2006","total_votes":121384,"poll_pct":68.2,"margin":1650},"pernambut":{"total":188543,"source":"IndiaVotes / ECI, Tamil Nadu Assembly Election 2006","total_votes":131495,"poll_pct":69.7,"margin":16915},"vaniayambadi":{"total":189807,"source":"IndiaVotes / ECI, Tamil Nadu Assembly Election 2006","total_votes":131368,"poll_pct":69.2,"margin":24184},"natrampalli":{"total":210823,"source":"IndiaVotes / ECI, Tamil Nadu Assembly Election 2006","total_votes":154927,"poll_pct":73.5,"margin":17243},"chengam":{"total":175158,"source":"IndiaVotes / ECI, Tamil Nadu Assembly Election 2006","total_votes":124844,"poll_pct":71.3,"margin":10200},"thandarambattu":{"total":187339,"source":"IndiaVotes / ECI, Tamil Nadu Assembly Election 2006","total_votes":143980,"poll_pct":76.9,"margin":30701},"tiruvannamalai":{"total":215158,"source":"IndiaVotes / ECI, Tamil Nadu Assembly Election 2006","total_votes":150105,"poll_pct":69.8,"margin":12803},"kalasapakkam":{"total":181980,"source":"IndiaVotes / ECI, Tamil Nadu Assembly Election 2006","total_votes":142208,"poll_pct":78.1,"margin":7666},"polur":{"total":173999,"source":"IndiaVotes / ECI, Tamil Nadu Assembly Election 2006","total_votes":124642,"poll_pct":71.6,"margin":7544},"anaicut":{"total":190228,"source":"IndiaVotes / ECI, Tamil Nadu Assembly Election 2006","total_votes":131641,"poll_pct":69.2,"margin":53},"vellore":{"total":207448,"source":"IndiaVotes / ECI, Tamil Nadu Assembly Election 2006","total_votes":135370,"poll_pct":65.3,"margin":21837},"arni":{"total":184336,"source":"IndiaVotes / ECI, Tamil Nadu Assembly Election 2006","total_votes":141135,"poll_pct":76.6,"margin":12302},"cheyyar":{"total":169494,"source":"IndiaVotes / ECI, Tamil Nadu Assembly Election 2006","total_votes":135518,"poll_pct":80.0,"margin":4790},"vandavasi":{"total":174376,"source":"IndiaVotes / ECI, Tamil Nadu Assembly Election 2006","total_votes":124365,"poll_pct":71.3,"margin":22788},"peranamallur":{"total":170898,"source":"IndiaVotes / ECI, Tamil Nadu Assembly Election 2006","total_votes":121990,"poll_pct":71.4,"margin":6688},"melmalayanur":{"total":174345,"source":"IndiaVotes / ECI, Tamil Nadu Assembly Election 2006","total_votes":123976,"poll_pct":71.1,"margin":11301},"gingee":{"total":179189,"source":"IndiaVotes / ECI, Tamil Nadu Assembly Election 2006","total_votes":129948,"poll_pct":72.5,"margin":12933},"tindivanam":{"total":153528,"source":"IndiaVotes / ECI, Tamil Nadu Assembly Election 2006","total_votes":118765,"poll_pct":77.4,"margin":2208},"vanur":{"total":201206,"source":"IndiaVotes / ECI, Tamil Nadu Assembly Election 2006","total_votes":140886,"poll_pct":70.0,"margin":4036},"kandamangalam":{"total":186058,"source":"IndiaVotes / ECI, Tamil Nadu Assembly Election 2006","total_votes":139456,"poll_pct":75.0,"margin":7375},"villupuram":{"total":212630,"source":"IndiaVotes / ECI, Tamil Nadu Assembly Election 2006","total_votes":154617,"poll_pct":72.7,"margin":9748},"mugaiyur":{"total":188747,"source":"IndiaVotes / ECI, Tamil Nadu Assembly Election 2006","total_votes":128304,"poll_pct":68.0,"margin":19506},"thirunavalur":{"total":166440,"source":"IndiaVotes / ECI, Tamil Nadu Assembly Election 2006","total_votes":125884,"poll_pct":75.6,"margin":6187},"ulundurpet":{"total":214774,"source":"IndiaVotes / ECI, Tamil Nadu Assembly Election 2006","total_votes":149062,"poll_pct":69.4,"margin":18784},"nellikuppam":{"total":164369,"source":"IndiaVotes / ECI, Tamil Nadu Assembly Election 2006","total_votes":124369,"poll_pct":75.7,"margin":12080},"cuddalore":{"total":196095,"source":"IndiaVotes / ECI, Tamil Nadu Assembly Election 2006","total_votes":140291,"poll_pct":71.5,"margin":6266},"panruti":{"total":175294,"source":"IndiaVotes / ECI, Tamil Nadu Assembly Election 2006","total_votes":143153,"poll_pct":81.7,"margin":148},"kurinjipadi":{"total":167658,"source":"IndiaVotes / ECI, Tamil Nadu Assembly Election 2006","total_votes":123719,"poll_pct":73.8,"margin":1915},"bhuvanagiri":{"total":167859,"source":"IndiaVotes / ECI, Tamil Nadu Assembly Election 2006","total_votes":127867,"poll_pct":76.2,"margin":14823},"kattumannarkoil":{"total":152743,"source":"IndiaVotes / ECI, Tamil Nadu Assembly Election 2006","total_votes":111245,"poll_pct":72.8,"margin":13414},"chidambaram":{"total":147220,"source":"IndiaVotes / ECI, Tamil Nadu Assembly Election 2006","total_votes":111106,"poll_pct":75.5,"margin":16810},"vridhachalam":{"total":197117,"source":"IndiaVotes / ECI, Tamil Nadu Assembly Election 2006","total_votes":151752,"poll_pct":77.0,"margin":13777},"mangalore":{"total":193879,"source":"IndiaVotes / ECI, Tamil Nadu Assembly Election 2006","total_votes":142353,"poll_pct":73.4,"margin":6914},"rishivandiam":{"total":186451,"source":"IndiaVotes / ECI, Tamil Nadu Assembly Election 2006","total_votes":128194,"poll_pct":68.8,"margin":7935},"chinnasalem":{"total":179669,"source":"IndiaVotes / ECI, Tamil Nadu Assembly Election 2006","total_votes":132301,"poll_pct":73.6,"margin":20278},"sankarapuram":{"total":206139,"source":"IndiaVotes / ECI, Tamil Nadu Assembly Election 2006","total_votes":144844,"poll_pct":70.3,"margin":2466},"hosur":{"total":312387,"source":"IndiaVotes / ECI, Tamil Nadu Assembly Election 2006","total_votes":215476,"poll_pct":69.0,"margin":12551},"thalli":{"total":180674,"source":"IndiaVotes / ECI, Tamil Nadu Assembly Election 2006","total_votes":123936,"poll_pct":68.6,"margin":4595},"kaveripattinam":{"total":183149,"source":"IndiaVotes / ECI, Tamil Nadu Assembly Election 2006","total_votes":141183,"poll_pct":77.1,"margin":11734},"krishnagiri":{"total":197095,"source":"IndiaVotes / ECI, Tamil Nadu Assembly Election 2006","total_votes":140275,"poll_pct":71.2,"margin":18195},"bargur":{"total":197892,"source":"IndiaVotes / ECI, Tamil Nadu Assembly Election 2006","total_votes":143663,"poll_pct":72.6,"margin":3208},"harur":{"total":223534,"source":"IndiaVotes / ECI, Tamil Nadu Assembly Election 2006","total_votes":155411,"poll_pct":69.5,"margin":13693},"morappur":{"total":173038,"source":"IndiaVotes / ECI, Tamil Nadu Assembly Election 2006","total_votes":126784,"poll_pct":73.3,"margin":13191},"palacode":{"total":196330,"source":"IndiaVotes / ECI, Tamil Nadu Assembly Election 2006","total_votes":150907,"poll_pct":76.9,"margin":4844},"dharmapuri":{"total":215291,"source":"IndiaVotes / ECI, Tamil Nadu Assembly Election 2006","total_votes":147708,"poll_pct":68.6,"margin":30207},"pennagaram":{"total":208084,"source":"IndiaVotes / ECI, Tamil Nadu Assembly Election 2006","total_votes":149939,"poll_pct":72.1,"margin":26932},"mettur":{"total":198408,"source":"IndiaVotes / ECI, Tamil Nadu Assembly Election 2006","total_votes":138343,"poll_pct":69.7,"margin":11138},"taramangalam":{"total":200861,"source":"IndiaVotes / ECI, Tamil Nadu Assembly Election 2006","total_votes":141764,"poll_pct":70.6,"margin":12254},"omalur":{"total":188486,"source":"IndiaVotes / ECI, Tamil Nadu Assembly Election 2006","total_votes":134410,"poll_pct":71.3,"margin":3663},"yercaud":{"total":156742,"source":"IndiaVotes / ECI, Tamil Nadu Assembly Election 2006","total_votes":113690,"poll_pct":72.5,"margin":4107},"salem_i":{"total":206400,"source":"IndiaVotes / ECI, Tamil Nadu Assembly Election 2006","total_votes":156592,"poll_pct":75.9,"margin":12817},"salem_ii":{"total":250137,"source":"IndiaVotes / ECI, Tamil Nadu Assembly Election 2006","total_votes":180642,"poll_pct":72.2,"margin":14743},"veerapandi":{"total":268821,"source":"IndiaVotes / ECI, Tamil Nadu Assembly Election 2006","total_votes":212851,"poll_pct":79.2,"margin":1638},"panamarathupatty":{"total":209051,"source":"IndiaVotes / ECI, Tamil Nadu Assembly Election 2006","total_votes":164254,"poll_pct":78.6,"margin":3889},"attur":{"total":160786,"source":"IndiaVotes / ECI, Tamil Nadu Assembly Election 2006","total_votes":118449,"poll_pct":73.7,"margin":10432},"talavasal":{"total":182114,"source":"IndiaVotes / ECI, Tamil Nadu Assembly Election 2006","total_votes":132062,"poll_pct":72.5,"margin":10049},"rasipuram":{"total":187025,"source":"IndiaVotes / ECI, Tamil Nadu Assembly Election 2006","total_votes":137750,"poll_pct":73.7,"margin":4969},"sendamangalam":{"total":182451,"source":"IndiaVotes / ECI, Tamil Nadu Assembly Election 2006","total_votes":129252,"poll_pct":70.8,"margin":16534},"namakkal":{"total":212232,"source":"IndiaVotes / ECI, Tamil Nadu Assembly Election 2006","total_votes":143999,"poll_pct":67.8,"margin":8099},"kapilamalai":{"total":171751,"source":"IndiaVotes / ECI, Tamil Nadu Assembly Election 2006","total_votes":122862,"poll_pct":71.5,"margin":8947},"tiruchengode":{"total":296618,"source":"IndiaVotes / ECI, Tamil Nadu Assembly Election 2006","total_votes":212073,"poll_pct":71.5,"margin":116},"sankari":{"total":210731,"source":"IndiaVotes / ECI, Tamil Nadu Assembly Election 2006","total_votes":144693,"poll_pct":68.7,"margin":16420},"edapadi":{"total":222666,"source":"IndiaVotes / ECI, Tamil Nadu Assembly Election 2006","total_votes":169951,"poll_pct":76.3,"margin":6347},"mettupalayam":{"total":204170,"source":"IndiaVotes / ECI, Tamil Nadu Assembly Election 2006","total_votes":151547,"poll_pct":74.2,"margin":142},"avanashi":{"total":190450,"source":"IndiaVotes / ECI, Tamil Nadu Assembly Election 2006","total_votes":134556,"poll_pct":70.7,"margin":4539},"thondamuthur":{"total":420186,"source":"IndiaVotes / ECI, Tamil Nadu Assembly Election 2006","total_votes":297700,"poll_pct":70.8,"margin":9894},"singanallur":{"total":337398,"source":"IndiaVotes / ECI, Tamil Nadu Assembly Election 2006","total_votes":240273,"poll_pct":71.2,"margin":14},"coimbatore_west":{"total":140374,"source":"IndiaVotes / ECI, Tamil Nadu Assembly Election 2006","total_votes":100682,"poll_pct":71.7,"margin":14281},"coimbatore_east":{"total":157364,"source":"IndiaVotes / ECI, Tamil Nadu Assembly Election 2006","total_votes":109215,"poll_pct":69.4,"margin":6336},"perur":{"total":337402,"source":"IndiaVotes / ECI, Tamil Nadu Assembly Election 2006","total_votes":246809,"poll_pct":73.1,"margin":14235},"kinathukkadavu":{"total":156478,"source":"IndiaVotes / ECI, Tamil Nadu Assembly Election 2006","total_votes":117815,"poll_pct":75.3,"margin":5150},"pollachi":{"total":193283,"source":"IndiaVotes / ECI, Tamil Nadu Assembly Election 2006","total_votes":135724,"poll_pct":70.2,"margin":2946},"valparai":{"total":127872,"source":"IndiaVotes / ECI, Tamil Nadu Assembly Election 2006","total_votes":86326,"poll_pct":67.5,"margin":20979},"udumalpet":{"total":207409,"source":"IndiaVotes / ECI, Tamil Nadu Assembly Election 2006","total_votes":143617,"poll_pct":69.2,"margin":3463},"dharapuram":{"total":173547,"source":"IndiaVotes / ECI, Tamil Nadu Assembly Election 2006","total_votes":124587,"poll_pct":71.8,"margin":4712},"vellakoil":{"total":155431,"source":"IndiaVotes / ECI, Tamil Nadu Assembly Election 2006","total_votes":117629,"poll_pct":75.7,"margin":17088},"pongalur":{"total":154492,"source":"IndiaVotes / ECI, Tamil Nadu Assembly Election 2006","total_votes":114351,"poll_pct":74.0,"margin":53},"palladam":{"total":236223,"source":"IndiaVotes / ECI, Tamil Nadu Assembly Election 2006","total_votes":167088,"poll_pct":70.7,"margin":5517},"tiruppur":{"total":428422,"source":"IndiaVotes / ECI, Tamil Nadu Assembly Election 2006","total_votes":244208,"poll_pct":57.0,"margin":11299},"kangayam":{"total":162590,"source":"IndiaVotes / ECI, Tamil Nadu Assembly Election 2006","total_votes":123563,"poll_pct":76.0,"margin":7296},"modakurichi":{"total":192274,"source":"IndiaVotes / ECI, Tamil Nadu Assembly Election 2006","total_votes":146524,"poll_pct":76.2,"margin":3860},"perundurai":{"total":180617,"source":"IndiaVotes / ECI, Tamil Nadu Assembly Election 2006","total_votes":137506,"poll_pct":76.1,"margin":8578},"erode":{"total":303864,"source":"IndiaVotes / ECI, Tamil Nadu Assembly Election 2006","total_votes":214990,"poll_pct":70.8,"margin":10831},"bhavani":{"total":169720,"source":"IndiaVotes / ECI, Tamil Nadu Assembly Election 2006","total_votes":126612,"poll_pct":74.6,"margin":5103},"andhiyur":{"total":159908,"source":"IndiaVotes / ECI, Tamil Nadu Assembly Election 2006","total_votes":111199,"poll_pct":69.5,"margin":19743},"gobichettipalayam":{"total":157445,"source":"IndiaVotes / ECI, Tamil Nadu Assembly Election 2006","total_votes":121548,"poll_pct":77.2,"margin":4019},"bhavanisagar":{"total":170773,"source":"IndiaVotes / ECI, Tamil Nadu Assembly Election 2006","total_votes":128628,"poll_pct":75.3,"margin":20016},"sathyamangalam":{"total":171378,"source":"IndiaVotes / ECI, Tamil Nadu Assembly Election 2006","total_votes":121473,"poll_pct":70.9,"margin":15894},"coonoor":{"total":147524,"source":"IndiaVotes / ECI, Tamil Nadu Assembly Election 2006","total_votes":95670,"poll_pct":64.9,"margin":5714},"ootacamund":{"total":150906,"source":"IndiaVotes / ECI, Tamil Nadu Assembly Election 2006","total_votes":95800,"poll_pct":63.5,"margin":4559},"gudalur":{"total":210699,"source":"IndiaVotes / ECI, Tamil Nadu Assembly Election 2006","total_votes":143356,"poll_pct":68.0,"margin":20232},"palani":{"total":160854,"source":"IndiaVotes / ECI, Tamil Nadu Assembly Election 2006","total_votes":120434,"poll_pct":74.9,"margin":10909},"oddanchatram":{"total":159094,"source":"IndiaVotes / ECI, Tamil Nadu Assembly Election 2006","total_votes":118897,"poll_pct":74.7,"margin":19903},"periyakulam":{"total":195988,"source":"IndiaVotes / ECI, Tamil Nadu Assembly Election 2006","total_votes":137295,"poll_pct":70.1,"margin":14834},"theni":{"total":200448,"source":"IndiaVotes / ECI, Tamil Nadu Assembly Election 2006","total_votes":136691,"poll_pct":68.2,"margin":6983},"bodinayakkanur":{"total":165068,"source":"IndiaVotes / ECI, Tamil Nadu Assembly Election 2006","total_votes":117392,"poll_pct":71.1,"margin":898},"cumbum":{"total":165427,"source":"IndiaVotes / ECI, Tamil Nadu Assembly Election 2006","total_votes":117435,"poll_pct":71.0,"margin":1958},"andipatti":{"total":183610,"source":"IndiaVotes / ECI, Tamil Nadu Assembly Election 2006","total_votes":134307,"poll_pct":73.1,"margin":25186},"sedapatti":{"total":138459,"source":"IndiaVotes / ECI, Tamil Nadu Assembly Election 2006","total_votes":97990,"poll_pct":70.8,"margin":2049},"thirumangalam":{"total":169523,"source":"IndiaVotes / ECI, Tamil Nadu Assembly Election 2006","total_votes":120251,"poll_pct":70.9,"margin":4144},"usilampatti":{"total":137738,"source":"IndiaVotes / ECI, Tamil Nadu Assembly Election 2006","total_votes":92508,"poll_pct":67.2,"margin":3045},"nilakottai":{"total":176484,"source":"IndiaVotes / ECI, Tamil Nadu Assembly Election 2006","total_votes":122873,"poll_pct":69.6,"margin":6284},"sholavandan":{"total":158021,"source":"IndiaVotes / ECI, Tamil Nadu Assembly Election 2006","total_votes":112702,"poll_pct":71.3,"margin":1586},"tirupparankundram":{"total":388164,"source":"IndiaVotes / ECI, Tamil Nadu Assembly Election 2006","total_votes":274018,"poll_pct":70.6,"margin":12686},"madurai_west":{"total":185269,"source":"IndiaVotes / ECI, Tamil Nadu Assembly Election 2006","total_votes":131030,"poll_pct":70.7,"margin":3467},"madurai_central":{"total":135020,"source":"IndiaVotes / ECI, Tamil Nadu Assembly Election 2006","total_votes":94232,"poll_pct":69.8,"margin":7193},"madurai_east":{"total":134455,"source":"IndiaVotes / ECI, Tamil Nadu Assembly Election 2006","total_votes":95253,"poll_pct":70.8,"margin":51},"samayanallur":{"total":411325,"source":"IndiaVotes / ECI, Tamil Nadu Assembly Election 2006","total_votes":286928,"poll_pct":69.8,"margin":5644},"melur":{"total":190114,"source":"IndiaVotes / ECI, Tamil Nadu Assembly Election 2006","total_votes":135292,"poll_pct":71.2,"margin":3173},"natham":{"total":179371,"source":"IndiaVotes / ECI, Tamil Nadu Assembly Election 2006","total_votes":133615,"poll_pct":74.5,"margin":3760},"dindigul":{"total":218221,"source":"IndiaVotes / ECI, Tamil Nadu Assembly Election 2006","total_votes":152750,"poll_pct":70.0,"margin":18949},"athoor":{"total":202430,"source":"IndiaVotes / ECI, Tamil Nadu Assembly Election 2006","total_votes":143435,"poll_pct":70.9,"margin":26561},"vedasandur":{"total":210197,"source":"IndiaVotes / ECI, Tamil Nadu Assembly Election 2006","total_votes":149371,"poll_pct":71.1,"margin":14758},"aravakurichi":{"total":134828,"source":"IndiaVotes / ECI, Tamil Nadu Assembly Election 2006","total_votes":100789,"poll_pct":74.8,"margin":2825},"karur":{"total":221389,"source":"IndiaVotes / ECI, Tamil Nadu Assembly Election 2006","total_votes":170721,"poll_pct":77.1,"margin":5384},"krishnarayapuram":{"total":161374,"source":"IndiaVotes / ECI, Tamil Nadu Assembly Election 2006","total_votes":126055,"poll_pct":78.1,"margin":8934},"marungapuri":{"total":187713,"source":"IndiaVotes / ECI, Tamil Nadu Assembly Election 2006","total_votes":135095,"poll_pct":72.0,"margin":2532},"kulithalai":{"total":171539,"source":"IndiaVotes / ECI, Tamil Nadu Assembly Election 2006","total_votes":138082,"poll_pct":80.5,"margin":13989},"thottiam":{"total":165785,"source":"IndiaVotes / ECI, Tamil Nadu Assembly Election 2006","total_votes":123688,"poll_pct":74.6,"margin":53},"uppiliapuram":{"total":173935,"source":"IndiaVotes / ECI, Tamil Nadu Assembly Election 2006","total_votes":126151,"poll_pct":72.5,"margin":12382},"musiri":{"total":203080,"source":"IndiaVotes / ECI, Tamil Nadu Assembly Election 2006","total_votes":153756,"poll_pct":75.7,"margin":10927},"lalgudi":{"total":174305,"source":"IndiaVotes / ECI, Tamil Nadu Assembly Election 2006","total_votes":132221,"poll_pct":75.9,"margin":3557},"perambalur":{"total":181069,"source":"IndiaVotes / ECI, Tamil Nadu Assembly Election 2006","total_votes":133879,"poll_pct":73.9,"margin":6638},"varahur":{"total":160287,"source":"IndiaVotes / ECI, Tamil Nadu Assembly Election 2006","total_votes":121148,"poll_pct":75.6,"margin":2543},"ariyalur":{"total":163907,"source":"IndiaVotes / ECI, Tamil Nadu Assembly Election 2006","total_votes":132472,"poll_pct":80.8,"margin":4194},"andimadam":{"total":144606,"source":"IndiaVotes / ECI, Tamil Nadu Assembly Election 2006","total_votes":113467,"poll_pct":78.5,"margin":5828},"jayankondam":{"total":167088,"source":"IndiaVotes / ECI, Tamil Nadu Assembly Election 2006","total_votes":135066,"poll_pct":80.8,"margin":2051},"srirangam":{"total":259848,"source":"IndiaVotes / ECI, Tamil Nadu Assembly Election 2006","total_votes":193882,"poll_pct":74.6,"margin":10922},"tiruchirapalli_i":{"total":117649,"source":"IndiaVotes / ECI, Tamil Nadu Assembly Election 2006","total_votes":86814,"poll_pct":73.8,"margin":10451},"tiruchirapalli_ii":{"total":211217,"source":"IndiaVotes / ECI, Tamil Nadu Assembly Election 2006","total_votes":150019,"poll_pct":71.0,"margin":16632},"thiruverambur":{"total":266993,"source":"IndiaVotes / ECI, Tamil Nadu Assembly Election 2006","total_votes":189936,"poll_pct":71.1,"margin":24762},"sirkali":{"total":172456,"source":"IndiaVotes / ECI, Tamil Nadu Assembly Election 2006","total_votes":123824,"poll_pct":71.8,"margin":3791},"poompuhar":{"total":161553,"source":"IndiaVotes / ECI, Tamil Nadu Assembly Election 2006","total_votes":120017,"poll_pct":74.3,"margin":964},"mayuram":{"total":159101,"source":"IndiaVotes / ECI, Tamil Nadu Assembly Election 2006","total_votes":115628,"poll_pct":72.7,"margin":1578},"kuttalam":{"total":167513,"source":"IndiaVotes / ECI, Tamil Nadu Assembly Election 2006","total_votes":129125,"poll_pct":77.1,"margin":11605},"nannilam":{"total":166654,"source":"IndiaVotes / ECI, Tamil Nadu Assembly Election 2006","total_votes":127511,"poll_pct":76.5,"margin":11566},"tiruvarur":{"total":176537,"source":"IndiaVotes / ECI, Tamil Nadu Assembly Election 2006","total_votes":135470,"poll_pct":76.7,"margin":26933},"nagapattinam":{"total":164819,"source":"IndiaVotes / ECI, Tamil Nadu Assembly Election 2006","total_votes":125072,"poll_pct":75.9,"margin":2344},"vedaranyam":{"total":159520,"source":"IndiaVotes / ECI, Tamil Nadu Assembly Election 2006","total_votes":133076,"poll_pct":83.4,"margin":6531},"tiruthuraipundi":{"total":180937,"source":"IndiaVotes / ECI, Tamil Nadu Assembly Election 2006","total_votes":137881,"poll_pct":76.2,"margin":22706},"mannargudi":{"total":183489,"source":"IndiaVotes / ECI, Tamil Nadu Assembly Election 2006","total_votes":137898,"poll_pct":75.2,"margin":6958},"pattukkottai":{"total":176850,"source":"IndiaVotes / ECI, Tamil Nadu Assembly Election 2006","total_votes":126021,"poll_pct":71.3,"margin":15334},"peravurani":{"total":168565,"source":"IndiaVotes / ECI, Tamil Nadu Assembly Election 2006","total_votes":129809,"poll_pct":77.0,"margin":3606},"orathanad":{"total":165978,"source":"IndiaVotes / ECI, Tamil Nadu Assembly Election 2006","total_votes":128642,"poll_pct":77.5,"margin":3843},"thiruvonam":{"total":200113,"source":"IndiaVotes / ECI, Tamil Nadu Assembly Election 2006","total_votes":149991,"poll_pct":75.0,"margin":1805},"thanjavur":{"total":185684,"source":"IndiaVotes / ECI, Tamil Nadu Assembly Election 2006","total_votes":123302,"poll_pct":66.4,"margin":11246},"tiruvaiyaru":{"total":149967,"source":"IndiaVotes / ECI, Tamil Nadu Assembly Election 2006","total_votes":114915,"poll_pct":76.6,"margin":366},"papanasam":{"total":161259,"source":"IndiaVotes / ECI, Tamil Nadu Assembly Election 2006","total_votes":123262,"poll_pct":76.4,"margin":7001},"valangiman":{"total":139552,"source":"IndiaVotes / ECI, Tamil Nadu Assembly Election 2006","total_votes":109987,"poll_pct":78.8,"margin":1633},"kumbakonam":{"total":166196,"source":"IndiaVotes / ECI, Tamil Nadu Assembly Election 2006","total_votes":125132,"poll_pct":75.3,"margin":14141},"thiruvidamarudur":{"total":174917,"source":"IndiaVotes / ECI, Tamil Nadu Assembly Election 2006","total_votes":134714,"poll_pct":77.0,"margin":3768},"thirumayam":{"total":162477,"source":"IndiaVotes / ECI, Tamil Nadu Assembly Election 2006","total_votes":117989,"poll_pct":72.6,"margin":314},"kolathur":{"total":197012,"source":"IndiaVotes / ECI, Tamil Nadu Assembly Election 2006","total_votes":148095,"poll_pct":75.2,"margin":6268},"pudukkottai":{"total":202027,"source":"IndiaVotes / ECI, Tamil Nadu Assembly Election 2006","total_votes":152508,"poll_pct":75.5,"margin":1950},"alangudi":{"total":197741,"source":"IndiaVotes / ECI, Tamil Nadu Assembly Election 2006","total_votes":152998,"poll_pct":77.4,"margin":9151},"arantangi":{"total":205474,"source":"IndiaVotes / ECI, Tamil Nadu Assembly Election 2006","total_votes":144519,"poll_pct":70.3,"margin":17460},"tiruppattur_41":{"total":210399,"source":"IndiaVotes / ECI, Tamil Nadu Assembly Election 2006","total_votes":147772,"poll_pct":70.2,"margin":13739},"tiruppattur_194":{"total":210399,"source":"IndiaVotes / ECI, Tamil Nadu Assembly Election 2006","total_votes":147772,"poll_pct":70.2,"margin":5627},"karaikudi":{"total":208583,"source":"IndiaVotes / ECI, Tamil Nadu Assembly Election 2006","total_votes":132196,"poll_pct":63.4,"margin":16246},"tiruvadanai":{"total":178964,"source":"IndiaVotes / ECI, Tamil Nadu Assembly Election 2006","total_votes":117715,"poll_pct":65.8,"margin":5253},"ilayangudi":{"total":145800,"source":"IndiaVotes / ECI, Tamil Nadu Assembly Election 2006","total_votes":97465,"poll_pct":66.8,"margin":12706},"sivaganga":{"total":184172,"source":"IndiaVotes / ECI, Tamil Nadu Assembly Election 2006","total_votes":115731,"poll_pct":62.8,"margin":6113},"manamadurai":{"total":179349,"source":"IndiaVotes / ECI, Tamil Nadu Assembly Election 2006","total_votes":109458,"poll_pct":61.0,"margin":11455},"paramakudi":{"total":169035,"source":"IndiaVotes / ECI, Tamil Nadu Assembly Election 2006","total_votes":112645,"poll_pct":66.6,"margin":1054},"ramanathapuram":{"total":210426,"source":"IndiaVotes / ECI, Tamil Nadu Assembly Election 2006","total_votes":144159,"poll_pct":68.5,"margin":13367},"kadaladi":{"total":204370,"source":"IndiaVotes / ECI, Tamil Nadu Assembly Election 2006","total_votes":119433,"poll_pct":58.4,"margin":7556},"mudukulathur":{"total":173271,"source":"IndiaVotes / ECI, Tamil Nadu Assembly Election 2006","total_votes":103723,"poll_pct":59.9,"margin":10521},"aruppukottai":{"total":161711,"source":"IndiaVotes / ECI, Tamil Nadu Assembly Election 2006","total_votes":115968,"poll_pct":71.7,"margin":8234},"sattur":{"total":204350,"source":"IndiaVotes / ECI, Tamil Nadu Assembly Election 2006","total_votes":149256,"poll_pct":73.0,"margin":20845},"virudhunagar":{"total":182473,"source":"IndiaVotes / ECI, Tamil Nadu Assembly Election 2006","total_votes":130421,"poll_pct":71.5,"margin":4107},"sivakasi":{"total":253957,"source":"IndiaVotes / ECI, Tamil Nadu Assembly Election 2006","total_votes":183151,"poll_pct":72.1,"margin":9271},"srivilliputhur":{"total":186842,"source":"IndiaVotes / ECI, Tamil Nadu Assembly Election 2006","total_votes":135696,"poll_pct":72.6,"margin":6616},"rajapalayam":{"total":200783,"source":"IndiaVotes / ECI, Tamil Nadu Assembly Election 2006","total_votes":148266,"poll_pct":73.8,"margin":493},"vilathikulam":{"total":147823,"source":"IndiaVotes / ECI, Tamil Nadu Assembly Election 2006","total_votes":97226,"poll_pct":65.8,"margin":7654},"pottapidaram":{"total":144568,"source":"IndiaVotes / ECI, Tamil Nadu Assembly Election 2006","total_votes":98449,"poll_pct":68.1,"margin":9444},"koilpatti":{"total":176858,"source":"IndiaVotes / ECI, Tamil Nadu Assembly Election 2006","total_votes":114480,"poll_pct":64.7,"margin":12339},"sankaranayanarkoil":{"total":180575,"source":"IndiaVotes / ECI, Tamil Nadu Assembly Election 2006","total_votes":125560,"poll_pct":69.5,"margin":4442},"vasudevanallur":{"total":161517,"source":"IndiaVotes / ECI, Tamil Nadu Assembly Election 2006","total_votes":113716,"poll_pct":70.4,"margin":6759},"kadayanallur":{"total":175786,"source":"IndiaVotes / ECI, Tamil Nadu Assembly Election 2006","total_votes":120485,"poll_pct":68.5,"margin":4314},"tenkasi":{"total":186929,"source":"IndiaVotes / ECI, Tamil Nadu Assembly Election 2006","total_votes":140149,"poll_pct":75.0,"margin":18658},"alangulam":{"total":183349,"source":"IndiaVotes / ECI, Tamil Nadu Assembly Election 2006","total_votes":135689,"poll_pct":74.0,"margin":6845},"tirunelveli":{"total":198312,"source":"IndiaVotes / ECI, Tamil Nadu Assembly Election 2006","total_votes":142918,"poll_pct":72.1,"margin":606},"palayamcottai":{"total":232395,"source":"IndiaVotes / ECI, Tamil Nadu Assembly Election 2006","total_votes":148900,"poll_pct":64.1,"margin":41299},"cheranmahadevi":{"total":158911,"source":"IndiaVotes / ECI, Tamil Nadu Assembly Election 2006","total_votes":110996,"poll_pct":69.8,"margin":6032},"ambasamudram":{"total":162742,"source":"IndiaVotes / ECI, Tamil Nadu Assembly Election 2006","total_votes":108069,"poll_pct":66.4,"margin":15731},"nanguneri":{"total":159393,"source":"IndiaVotes / ECI, Tamil Nadu Assembly Election 2006","total_votes":104675,"poll_pct":65.7,"margin":20075},"radhapuram":{"total":173633,"source":"IndiaVotes / ECI, Tamil Nadu Assembly Election 2006","total_votes":113589,"poll_pct":65.4,"margin":10697},"sattangulam":{"total":130239,"source":"IndiaVotes / ECI, Tamil Nadu Assembly Election 2006","total_votes":87092,"poll_pct":66.9,"margin":15508},"tiruchendur":{"total":166975,"source":"IndiaVotes / ECI, Tamil Nadu Assembly Election 2006","total_votes":111713,"poll_pct":66.9,"margin":13916},"srivaikuntam":{"total":140639,"source":"IndiaVotes / ECI, Tamil Nadu Assembly Election 2006","total_votes":93648,"poll_pct":66.6,"margin":1632},"tuticorin":{"total":242170,"source":"IndiaVotes / ECI, Tamil Nadu Assembly Election 2006","total_votes":157484,"poll_pct":65.0,"margin":15323},"kanniyakumari":{"total":176033,"source":"IndiaVotes / ECI, Tamil Nadu Assembly Election 2006","total_votes":126225,"poll_pct":71.7,"margin":10687},"nagercoil":{"total":191270,"source":"IndiaVotes / ECI, Tamil Nadu Assembly Election 2006","total_votes":119334,"poll_pct":62.4,"margin":13745},"colachel":{"total":174762,"source":"IndiaVotes / ECI, Tamil Nadu Assembly Election 2006","total_votes":107866,"poll_pct":61.7,"margin":21320},"padmanabhapuram":{"total":155950,"source":"IndiaVotes / ECI, Tamil Nadu Assembly Election 2006","total_votes":97286,"poll_pct":62.4,"margin":31066},"thiruvattar":{"total":165801,"source":"IndiaVotes / ECI, Tamil Nadu Assembly Election 2006","total_votes":110791,"poll_pct":66.8,"margin":28050},"vilavancode":{"total":195426,"source":"IndiaVotes / ECI, Tamil Nadu Assembly Election 2006","total_votes":120076,"poll_pct":61.4,"margin":45074},"killiyoor":{"total":154732,"source":"IndiaVotes / ECI, Tamil Nadu Assembly Election 2006","total_votes":92456,"poll_pct":59.8,"margin":26605}}